README.rst
setup.py
aticonfig_indicator/__init__.py
aticonfig_indicator/indicator.py
aticonfig_indicator/utils.py
aticonfig_indicator.egg-info/PKG-INFO
aticonfig_indicator.egg-info/SOURCES.txt
aticonfig_indicator.egg-info/dependency_links.txt
aticonfig_indicator.egg-info/top_level.txt
bin/aticonfig-indicator