Metadata-Version: 1.0
Name: aticonfig-indicator
Version: 0.2.1
Summary: Aticonfig Temp Indicator on Unity desktop.
Home-page: https://github.com/syntaxsugar/aticonfig-indicator
Author: Jaromir Fojtu
Author-email: jaromir.fojtu@gmail.com
License: BSD
Platform: Ubuntu
